README.rst
setup.py
django_ajax/__init__.py
django_ajax/ajax_processors.py
django_ajax/config.py
django_ajax/context_processors.py
django_ajax/decorators.py
django_ajax/session_urls.py
django_ajax/utils.py
django_ajax/views.py
django_ajax.egg-info/PKG-INFO
django_ajax.egg-info/SOURCES.txt
django_ajax.egg-info/dependency_links.txt
django_ajax.egg-info/requires.txt
django_ajax.egg-info/top_level.txt
django_ajax/templatetags/__init__.py
django_ajax/templatetags/django_ajax_tags.py